gguf_frontend/__init__.py
gguf_frontend/__main__.py
gguf_frontend-0.0.3.dist-info/LICENSE
gguf_frontend-0.0.3.dist-info/WHEEL
gguf_frontend-0.0.3.dist-info/METADATA
gguf_frontend-0.0.3.dist-info/RECORD
