Metadata-Version: 2.1
Name: gguf-frontend
Version: 0.0.3
Summary: frontend
Author-email: calcuis <info@calcu.io>
Classifier: License :: OSI Approved :: MIT License
Project-URL: Repository, https://github.com/calcuis/simple-image-generator-frontend
